tests/__init__.py
tests/conftest.py
tests/test_understat.py
tests/test_utils.py
understat/__init__.py
understat/constants.py
understat/understat.py
understat/utils.py
understat-0.1.12.dist-info/AUTHORS.rst
understat-0.1.12.dist-info/LICENSE
understat-0.1.12.dist-info/METADATA
understat-0.1.12.dist-info/WHEEL
understat-0.1.12.dist-info/top_level.txt
understat-0.1.12.dist-info/RECORD
