Metadata-Version: 2.1
Name: understat
Version: 0.1.12
Summary: A Python wrapper for https://understat.com/
Home-page: https://github.com/amosbastian/understat
Author: amosbastian
Author-email: amosbastian@gmail.com
License: MIT
Project-URL: Documentation, http://fpl.readthedocs.io/en/latest/
Project-URL: Source, https://github.com/amosbastian/fpl
Keywords: fpl fantasy premier league understat football
Classifier: Development Status :: 4 - Beta
Classifier: Intended Audience :: Developers
Classifier: License :: OSI Approved :: MIT License
Classifier: Programming Language :: Python :: 3.6
Classifier: Programming Language :: Python :: 3.7
Classifier: Programming Language :: Python :: 3.8
Classifier: Programming Language :: Python :: 3.9
License-File: LICENSE
License-File: AUTHORS.rst
Requires-Dist: beautifulsoup4==4.11.1
Requires-Dist: pytest-aiohttp==1.0.4
Requires-Dist: pytest-cov==4.0.0
Requires-Dist: pytest-mock==3.6.0
Requires-Dist: pytest==7.2.0
Requires-Dist: aiohttp==3.8.3
